config_reader/__init__.py
config_reader/exceptions.py
config_reader/reader.py
config_reader/__pycache__/__init__.cpython-35.pyc
config_reader/__pycache__/reader.cpython-35.pyc
config_reader-0.8.dist-info/DESCRIPTION.rst
config_reader-0.8.dist-info/METADATA
config_reader-0.8.dist-info/RECORD
config_reader-0.8.dist-info/WHEEL
config_reader-0.8.dist-info/metadata.json
config_reader-0.8.dist-info/top_level.txt
