Metadata-Version: 2.0
Name: config-reader
Version: 0.8
Summary: A Python JSON-file config reader
Home-page: http://github.com/dubsmash/config-reader
Author: Dubsmash Team
Author-email: opensource@dubsmash.com
License: Apache
Download-URL: https://pypi.python.org/pypi/config-reader/
Platform: UNKNOWN
Classifier: Development Status :: 5 - Production/Stable
Classifier: Environment :: Web Environment
Classifier: Intended Audience :: Developers
Classifier: License :: OSI Approved :: MIT License
Classifier: Operating System :: OS Independent
Classifier: Programming Language :: Python
Classifier: Topic :: Internet :: WWW/HTTP
Requires-Dist: PyYAML
Requires-Dist: future
